myenv/__init__.py
myenv/setup.py
myenv/update_founder.py
found_update-1.16.dist-info/METADATA
found_update-1.16.dist-info/WHEEL
found_update-1.16.dist-info/top_level.txt
found_update-1.16.dist-info/RECORD
