Metadata-Version: 2.1
Name: found_update
Version: 1.16
Summary: A Python package for automatic updating tools.
Home-page: https://github.com/Pytholearn/found_update
Author: Pytholearn-HAZARD(ilia alizade)
Author-email: police123456789ilia@gmail.com
Classifier: Programming Language :: Python :: 3
Classifier: License :: OSI Approved :: MIT License
Classifier: Operating System :: OS Independent
Requires-Python: >=3.6
